unicms_unical_storage_handler/__init__.py
unicms_unical_storage_handler/apps.py
unicms_unical_storage_handler/handlers.py
unicms_unical_storage_handler/settings.py
unicms_unical_storage_handler/tests.py
unicms_unical_storage_handler/locale/it/LC_MESSAGES/django.mo
unicms_unical_storage_handler/locale/it/LC_MESSAGES/django.po
unicms_unical_storage_handler/static/js/unicms_ush_utils.js
unicms_unical_storage_handler/static/js/vue-markdown.js
unicms_unical_storage_handler/templates/storage_activity.html
unicms_unical_storage_handler/templates/storage_addressbook_info.html
unicms_unical_storage_handler/templates/storage_addressbook_list.html
unicms_unical_storage_handler/templates/storage_applied_research_line_list.html
unicms_unical_storage_handler/templates/storage_base.html
unicms_unical_storage_handler/templates/storage_base_research_line_list.html
unicms_unical_storage_handler/templates/storage_cdsinfo.html
unicms_unical_storage_handler/templates/storage_cdslist.html
unicms_unical_storage_handler/templates/storage_laboratory_info.html
unicms_unical_storage_handler/templates/storage_laboratory_list.html
unicms_unical_storage_handler/templates/storage_patents_list.html
unicms_unical_storage_handler/templates/storage_publications_info.html
unicms_unical_storage_handler/templates/storage_publications_list.html
unicms_unical_storage_handler/templates/storage_research_group_list.html
unicms_unical_storage_handler/templates/storage_spinoff_info.html
unicms_unical_storage_handler/templates/storage_spinoff_list.html
unicms_unical_storage_handler/templates/storage_structure_info.html
unicms_unical_storage_handler/templates/storage_structure_list.html
unicms_unical_storage_handler/templates/storage_teachers_info.html
unicms_unical_storage_handler/templates/storage_teachers_list.html
unicms_unical_storage_handler/templates/bases/unical_storage_list.html
unicms_unical_storage_handler/templates/bases/unical_storage_right_col.html
unicms_unical_storage_handler-0.8.3.dist-info/AUTHORS
unicms_unical_storage_handler-0.8.3.dist-info/LICENSE
unicms_unical_storage_handler-0.8.3.dist-info/METADATA
unicms_unical_storage_handler-0.8.3.dist-info/WHEEL
unicms_unical_storage_handler-0.8.3.dist-info/top_level.txt
unicms_unical_storage_handler-0.8.3.dist-info/RECORD
